ivcap_client/__init__.py
ivcap_client/agent.py
ivcap_client/api/__init__.py
ivcap_client/api/artifact/__init__.py
ivcap_client/api/artifact/artifact_list.py
ivcap_client/api/artifact/artifact_read.py
ivcap_client/api/artifact/artifact_upload.py
ivcap_client/api/aspect/__init__.py
ivcap_client/api/aspect/aspect_create.py
ivcap_client/api/aspect/aspect_list.py
ivcap_client/api/aspect/aspect_read.py
ivcap_client/api/aspect/aspect_retract.py
ivcap_client/api/aspect/aspect_update.py
ivcap_client/api/dashboard/__init__.py
ivcap_client/api/dashboard/dashboard_list.py
ivcap_client/api/metadata/__init__.py
ivcap_client/api/metadata/metadata_add.py
ivcap_client/api/metadata/metadata_list.py
ivcap_client/api/metadata/metadata_read.py
ivcap_client/api/metadata/metadata_revoke.py
ivcap_client/api/metadata/metadata_update_record.py
ivcap_client/api/openapi/__init__.py
ivcap_client/api/openapi/openapi_1openapiopenapi3_json.py
ivcap_client/api/order/__init__.py
ivcap_client/api/order/order_create.py
ivcap_client/api/order/order_list.py
ivcap_client/api/order/order_logs.py
ivcap_client/api/order/order_metadata.py
ivcap_client/api/order/order_products.py
ivcap_client/api/order/order_read.py
ivcap_client/api/order/order_top.py
ivcap_client/api/package/__init__.py
ivcap_client/api/package/package_list.py
ivcap_client/api/package/package_pull.py
ivcap_client/api/package/package_push.py
ivcap_client/api/package/package_remove.py
ivcap_client/api/package/package_status.py
ivcap_client/api/project/__init__.py
ivcap_client/api/project/project__create_project.py
ivcap_client/api/project/project__default_project.py
ivcap_client/api/project/project__list_project_members.py
ivcap_client/api/project/project__project_account.py
ivcap_client/api/project/project__remove_membership.py
ivcap_client/api/project/project__set_default_project.py
ivcap_client/api/project/project__set_project_account.py
ivcap_client/api/project/project__update_membership.py
ivcap_client/api/project/project_delete.py
ivcap_client-0.47.9.dist-info/AUTHORS.md
ivcap_client-0.47.9.dist-info/LICENSE
ivcap_client-0.47.9.dist-info/METADATA
ivcap_client-0.47.9.dist-info/WHEEL
ivcap_client-0.47.9.dist-info/RECORD
