Metadata-Version: 2.3
Name: ivcap_client
Version: 0.47.9
Summary: A client library for accessing an IVCAP cluster
Author: Max Ott
Author-email: max.ott@csiro.au
Requires-Python: >=3.10,<4.0
Classifier: Programming Language :: Python :: 3
Classifier: Programming Language :: Python :: 3.10
Classifier: Programming Language :: Python :: 3.11
Classifier: Programming Language :: Python :: 3.12
Classifier: Programming Language :: Python :: 3.13
Requires-Dist: attrs (>=21.3.0)
Requires-Dist: httpx (>=0.15.4,<0.29)
Requires-Dist: python-dateutil (>=2.8.0,<2.9.0)
Requires-Dist: tuspy (>=1.0.0)
